rapid/urls.py
rapid/registry.pyc
rapid/registry.py
rapid/models.pyc
rapid/forms.py
rapid/__init__.pyc
rapid/filters.py
rapid/wrappers.pyc
rapid/tests.py
rapid/widgets.py
rapid/models.py
rapid/permissions.py
rapid/wrappers.py
rapid/__init__.py
rapid/views.py
rapid/templates/rapid/main_window.html
rapid/templates/rapid/widgets/single-selector.html
rapid/templates/rapid/widgets/multiple-selector.html
rapid/templates/rapid/overlay/call.html
rapid/templates/rapid/overlay/register.html
rapid/templates/rapid/overlay/text.html
rapid/templates/rapid/list/instance_actions.html
rapid/templates/rapid/list/pagination.html
rapid/templates/rapid/list/show_value.html
rapid/templates/rapid/list/field_header.html
rapid/templates/rapid/bare/list.html
rapid/templates/rapid/bare/create.html
rapid/templates/rapid/bare/update.html
rapid/templates/rapid/bare/select.html
rapid/templates/rapid/bare/delete.html
rapid/templates/rapid/bare/detail.html
rapid/templates/rapid/filters/register.html
rapid/templates/rapid/filters/icon.html
rapid/templates/rapid/filters/key_value.html
rapid/templates/rapid/filters/model_filters.html
rapid/templates/rapid/filters/column_selector.html
rapid/templatetags/rapid_menu.py
rapid/templatetags/rapid_filters.py
rapid/templatetags/rapid_crud.py
rapid/templatetags/rapid_list.py
rapid/templatetags/__init__.py
rapid/migrations/__init__.py
rapid/fixtures/register_rapid.json
rapid_django-0.0.1.dev2.dist-info/DESCRIPTION.rst
rapid_django-0.0.1.dev2.dist-info/top_level.txt
rapid_django-0.0.1.dev2.dist-info/WHEEL
rapid_django-0.0.1.dev2.dist-info/RECORD
rapid_django-0.0.1.dev2.dist-info/metadata.json
rapid_django-0.0.1.dev2.dist-info/METADATA
