Metadata-Version: 2.0
Name: rapid-django
Version: 0.0.1.dev2
Summary: Opionated tools for rapid development of enterprise CRUD portals
Home-page: https://marcosdumay.com/rapid-django
Author: Marcos Dumay de Medeiros
Author-email: marcos@marcosdumay.com
License: MIT
Keywords: CRUD
Platform: UNKNOWN
Classifier: Development Status :: 2 - Pre-Alpha
Classifier: Environment :: Web Environment
Classifier: Framework :: Django :: 1.8
Classifier: Intended Audience :: Developers
Classifier: Topic :: Software Development :: Build Tools
Classifier: License :: OSI Approved :: MIT License
Classifier: Natural Language :: Portuguese (Brazilian)
Classifier: Operating System :: OS Independent
Classifier: Programming Language :: Python :: 2
Classifier: Programming Language :: Python :: 2.6
Classifier: Programming Language :: Python :: 2.7
Requires-Dist: django (>=1.8)
